integratethis/__init__.py
integratethis-2024.6.23.1.dist-info/LICENSE.txt
integratethis-2024.6.23.1.dist-info/METADATA
integratethis-2024.6.23.1.dist-info/WHEEL
integratethis-2024.6.23.1.dist-info/entry_points.txt
integratethis-2024.6.23.1.dist-info/RECORD
