Metadata-Version: 2.1
Name: integratethis
Version: 2024.6.23.1
Summary: Integrate programs or scripts into common tools like Windows Explorer context menu
License: GPL v3
Author: Karl Voit
Author-email: tools@Karl-Voit.at
Requires-Python: >=3.11,<4.0
Classifier: License :: Other/Proprietary License
Classifier: Programming Language :: Python :: 3
Classifier: Programming Language :: Python :: 3.11
